vulndigest/__init__.py
vulndigest/__main__.py
vulndigest/vulndigest_cli.py
vulndigest-1.0.0.dist-info/licenses/LICENSE
vulndigest-1.0.0.dist-info/METADATA
vulndigest-1.0.0.dist-info/WHEEL
vulndigest-1.0.0.dist-info/entry_points.txt
vulndigest-1.0.0.dist-info/top_level.txt
vulndigest-1.0.0.dist-info/RECORD
