Metadata-Version: 2.4
Name: VulnDigest
Version: 1.0.0
Summary: CLI tool to convert DAST JSON reports into readable Markdown summaries.
Author-email: Tyler Walker <tdwalker03@gmail.com>
License: MIT
Requires-Python: >=3.8
License-File: LICENSE
Requires-Dist: pydantic<2
Dynamic: license-file
